bsdotpy/__init__.py
bsdotpy/bsdotpy.py
bsdotpy/dataclasses.py
bsdotpy/errorhandlers.py
bsdotpy-0.1.2.dist-info/LICENSE
bsdotpy-0.1.2.dist-info/METADATA
bsdotpy-0.1.2.dist-info/WHEEL
bsdotpy-0.1.2.dist-info/top_level.txt
bsdotpy-0.1.2.dist-info/RECORD
