Metadata-Version: 2.1
Name: bsdotpy
Version: 0.1.2
Summary: BSDotPy, A module to get a bombsquad player's account data.
Home-page: https://github.com/FireHead90544/bsdotpy
Author: Rudransh Joshi
Author-email: rudranshjoshi1806@gmail.com
License: Apache License 2.0
Project-URL: Issue tracker, https://github.com/FireHead90544/bsdotpy/issues
Platform: any
Requires-Dist: requests
Requires-Dist: bs4
